minmodkg/__init__.py
minmodkg/api/__init__.py
minmodkg/api/__main__.py
minmodkg/api/dependencies.py
minmodkg/api/internal/__init__.py
minmodkg/api/internal/admin.py
minmodkg/api/main.py
minmodkg/api/models/__init__.py
minmodkg/api/models/public_dedup_mineral_site.py
minmodkg/api/models/public_mineral_site.py
minmodkg/api/models/public_user.py
minmodkg/api/routers/__init__.py
minmodkg/api/routers/cdr.py
minmodkg/api/routers/dedup_mineral_site.py
minmodkg/api/routers/entities.py
minmodkg/api/routers/lod.py
minmodkg/api/routers/login.py
minmodkg/api/routers/mineral_site.py
minmodkg/api/routers/stats.py
minmodkg/config.py
minmodkg/entity_linking.py
minmodkg/etl/__init__.py
minmodkg/etl/blazegraph.py
minmodkg/etl/fuseki.py
minmodkg/etl/kgrel_entity.py
minmodkg/etl/mineral_site.py
minmodkg/etl/postgres.py
minmodkg/etl/same_as.py
minmodkg/etl/virtuoso.py
minmodkg/extractors/.gitignore
minmodkg/extractors/__init__.py
minmodkg/grade_tonnage_model.py
minmodkg/integrations/__init__.py
minmodkg/integrations/cdr/__init__.py
minmodkg/integrations/cdr/__main__.py
minmodkg/integrations/cdr/cdr.ipynb
minmodkg/integrations/cdr/cdr.py
minmodkg/integrations/cdr/cdr_helper.py
minmodkg/integrations/cdr/cdr_schemas.py
minmodkg/integrations/fusemine/__init__.py
minmodkg/integrations/fusemine/__main__.py
minmodkg/libraries/__init__.py
minmodkg/libraries/rdf/__init__.py
minmodkg/libraries/rdf/blazegraph.py
minmodkg/libraries/rdf/fuseki.py
minmodkg/libraries/rdf/namespace.py
minmodkg/libraries/rdf/rdf_model.py
minmodkg/libraries/rdf/triple_store.py
minmodkg/libraries/rdf/virtuoso.py
minmodkg/misc/__init__.py
minmodkg/misc/deserializer.py
minmodkg/misc/exceptions.py
minmodkg/misc/geo.py
minmodkg/misc/prefix_index.py
minmodkg/misc/schema/__init__.py
minmodkg/misc/schema/make_diagram.py
minmodkg/misc/schema/make_shapes.py
minmodkg/misc/utils.py
minmodkg/models/__init__.py
minmodkg/models/kg/__init__.py
minmodkg/models/kg/base.py
minmodkg/models/kg/candidate_entity.py
minmodkg-2.7.1.dist-info/LICENSE
minmodkg-2.7.1.dist-info/METADATA
minmodkg-2.7.1.dist-info/WHEEL
minmodkg-2.7.1.dist-info/RECORD
