Metadata-Version: 2.1
Name: minmodkg
Version: 2.7.1
Summary: code repository for TA2 Knowledge Graph (MinMod) construction & deployment
License: MIT
Author: Binh Vu
Author-email: bvu687@gmail.com
Requires-Python: >=3.11,<4.0
Classifier: License :: OSI Approved :: MIT License
Classifier: Programming Language :: Python :: 3
Classifier: Programming Language :: Python :: 3.11
Classifier: Programming Language :: Python :: 3.12
Classifier: Programming Language :: Python :: 3.13
Requires-Dist: bcrypt (>=4.2.0,<5.0.0)
Requires-Dist: drepr-v2 (>=1.6.0,<2.0.0)
Requires-Dist: fastapi[standard] (>=0.115.3,<0.116.0)
Requires-Dist: htbuilder (>=0.6.2,<0.7.0)
Requires-Dist: httpx (>=0.28.1,<0.29.0)
Requires-Dist: jaydebeapi (>=1.2.3,<2.0.0)
Requires-Dist: networkx (>=3.2.1,<4.0.0)
Requires-Dist: pandas (>=2.2.2,<3.0.0)
Requires-Dist: psycopg[binary] (>=3.2.3,<4.0.0)
Requires-Dist: pyjwt (>=2.9.0,<3.0.0)
Requires-Dist: pyproj (>=3.6.1,<4.0.0)
Requires-Dist: serde2[all] (>=1.8.6,<2.0.0)
Requires-Dist: shapely (>=2.0.5,<3.0.0)
Requires-Dist: sqlalchemy (>=2.0.36,<3.0.0)
Requires-Dist: sqlmodel (>=0.0.22,<0.0.23)
Requires-Dist: statickg (>=1.13.1,<2.0.0)
Requires-Dist: timer4 (>=1.1.0,<2.0.0)
